<?xml version="1.0" encoding="UTF-8"?>
<kml xmlns="http://earth.google.com/kml/2.1">
<GroundOverlay z-index="1">
	<name>wrf-8-km</name>
	<color>ffffffff</color>
	<Icon>
		<href>https://github.com/AndroidUpscale/RainRadarUpscale/raw/master/citys2.png?ts=1508593782</href>
		<viewBoundScale>0.75</viewBoundScale>
	</Icon>
	<LatLonBox>
		<north>40.09185752806847</north>
		<south>11.79165682167668</south>
		<east>64.66130732195801</east>
		<west>29.64657256426859</west>
	</LatLonBox>
</GroundOverlay>
</kml>